infdate/__init__.py
infdate/py.typed
infdate-0.2.5.dist-info/METADATA
infdate-0.2.5.dist-info/WHEEL
infdate-0.2.5.dist-info/licenses/LICENSE
infdate-0.2.5.dist-info/RECORD
