Metadata-Version: 2.4
Name: infdate
Version: 0.2.5
Summary: Date object wrapper supporting infinity
Project-URL: Homepage, https://gitlab.com/blackstream-x/infdate
Project-URL: CI, https://gitlab.com/blackstream-x/infdate/-/pipelines
Project-URL: Bug Tracker, https://gitlab.com/blackstream-x/infdate/-/issues
Project-URL: Repository, https://gitlab.com/blackstream-x/infdate.git
Author-email: Rainer Schwarzbach <rainer@blackstream.de>
License-File: LICENSE
Classifier: Development Status :: 4 - Beta
Classifier: Intended Audience :: Developers
Classifier: License :: OSI Approved :: MIT License
Classifier: Operating System :: OS Independent
Classifier: Programming Language :: Python :: 3
Classifier: Programming Language :: Python :: 3 :: Only
Classifier: Programming Language :: Python :: 3.10
Classifier: Programming Language :: Python :: 3.11
Classifier: Programming Language :: Python :: 3.12
Classifier: Programming Language :: Python :: 3.13
Classifier: Programming Language :: Python :: 3.14
Classifier: Topic :: Software Development :: Libraries :: Python Modules
Requires-Python: >=3.10
